atils/__init__.py
atils/argocd.py
atils/atils_kubernetes.py
atils/build.py
atils/common/.secrets.yaml
atils/common/__init__.py
atils/common/config.py
atils/common/console_utils.py
atils/common/settings.py
atils/common/settings.yaml
atils/common/template_utils.py
atils/helm.py
atils/jobs.py
atils/templates/__init__.py
atils/templates/master-app.yaml
atils/test.py
atils_bin/__init__.py
atils_bin/atils.py
atils-1.5.1.dist-info/METADATA
atils-1.5.1.dist-info/WHEEL
atils-1.5.1.dist-info/entry_points.txt
atils-1.5.1.dist-info/RECORD
