Metadata-Version: 2.3
Name: atils
Version: 1.5.1
Summary: A series of scripts used to interact and work with this repository.
Author: Aidan Hilt
Author-email: aidanhilt2@gmail.com
Requires-Python: >=3.12,<3.13
Classifier: Programming Language :: Python :: 3
Classifier: Programming Language :: Python :: 3.12
Requires-Dist: argparse (>=1.4.0,<2.0.0)
Requires-Dist: colored (>=2.2.4,<3.0.0)
Requires-Dist: dynaconf (>=3.1.12,<4.0.0)
Requires-Dist: hvac (>=1.1.0,<2.0.0)
Requires-Dist: jinja2 (>=3.1.2,<4.0.0)
Requires-Dist: kubernetes (>=28.1.0,<29.0.0)
Requires-Dist: mypy (>=1.1.1,<2.0.0)
Requires-Dist: requests (>=2.29.0,<3.0.0)
Requires-Dist: rich (>=13.7.1,<14.0.0)
Requires-Dist: setuptools (>=75.0.0,<76.0.0)
Requires-Dist: shutils (>=0.1.0,<0.2.0)
Requires-Dist: termcolor (>=2.3.0,<3.0.0)
Requires-Dist: watchfiles (>=0.21.0,<0.22.0)
Project-URL: Homepage, https://github.com/AidanHilt/PersonalMonorepo/tree/master/atils
